mcp_server_appwrite/__init__.py
mcp_server_appwrite/__main__.py
mcp_server_appwrite/server.py
mcp_server_appwrite/service.py
mcp_server_appwrite/tool_manager.py
mseep_mcp_server_appwrite-0.2.2.dist-info/licenses/LICENSE
mseep_mcp_server_appwrite-0.2.2.dist-info/METADATA
mseep_mcp_server_appwrite-0.2.2.dist-info/WHEEL
mseep_mcp_server_appwrite-0.2.2.dist-info/entry_points.txt
mseep_mcp_server_appwrite-0.2.2.dist-info/top_level.txt
mseep_mcp_server_appwrite-0.2.2.dist-info/RECORD
